shaonutil/__init__.py
shaonutil/file.py
shaonutil/image.py
shaonutil/imgcode.py
shaonutil/math.py
shaonutil/mysqlDB.py
shaonutil/network.py
shaonutil/process.py
shaonutil/security.py
shaonutil/stats.py
shaonutil/strings.py
shaonutil/windows.py
shaonutil-0.0.0.70.1.dist-info/LICENSE
shaonutil-0.0.0.70.1.dist-info/METADATA
shaonutil-0.0.0.70.1.dist-info/WHEEL
shaonutil-0.0.0.70.1.dist-info/top_level.txt
shaonutil-0.0.0.70.1.dist-info/RECORD
