Metadata-Version: 2.1
Name: shaonutil
Version: 0.0.0.70.1
Summary: UNKNOWN
Home-page: https://github.com/ShaonMajumder/shaonutil
Author: Shaon Majumder
Author-email: smazoomder@gmail.com
License: UNKNOWN
Download-URL: https://github.com/ShaonMajumder/shaonutil/archive/0.0.0.70.1.tar.gz
Keywords: shaon,utility,statistics
Platform: UNKNOWN
